{
  "1": [
    {
      "word": "대인 관계",
      "translation": "межличностные отношения",
      "example": "좋은 대인 관계는 직장에서 중요해요.",
      "example_translation": "Хорошие отношения с людьми важны на работе."
    },
    {
      "word": "동료",
      "translation": "коллега",
      "example": "동료와 잘 지내는 것이 좋아요.",
      "example_translation": "Хорошо ладить с коллегами — это хорошо."
    }
  ],
  "2": [
    {
      "word": "성격",
      "translation": "характер",
      "example": "그 사람은 성격이 아주 좋아요.",
      "example_translation": "У того человека очень хороший характер."
    },
    {
      "word": "내성적이다",
      "translation": "быть интровертным",
      "example": "저는 내성적인 성격이에요.",
      "example_translation": "У меня интровертный характер."
    }
  ]
}